kollavarsham/__init__.py
kollavarsham/py.typed
kollavarsham/_jsii/__init__.py
kollavarsham/_jsii/kollavarsham@2.5.4.jsii.tgz
kollavarsham-2.5.4.dist-info/LICENSE
kollavarsham-2.5.4.dist-info/METADATA
kollavarsham-2.5.4.dist-info/WHEEL
kollavarsham-2.5.4.dist-info/top_level.txt
kollavarsham-2.5.4.dist-info/RECORD
