Metadata-Version: 2.1
Name: kollavarsham
Version: 2.5.4
Summary: Convert Gregorian date to Kollavarsham date and vice versa
Home-page: https://kollavarsham.org
Author: The Kollavarsham Team<info@kollavarsham.org>
License: MIT
Project-URL: Source, https://github.com/kollavarsham/kollavarsham-js.git
Platform: UNKNOWN
Classifier: Intended Audience :: Developers
Classifier: Operating System :: OS Independent
Classifier: Programming Language :: JavaScript
Classifier: Programming Language :: Python :: 3 :: Only
Classifier: Programming Language :: Python :: 3.7
Classifier: Programming Language :: Python :: 3.8
Classifier: Programming Language :: Python :: 3.9
Classifier: Programming Language :: Python :: 3.10
Classifier: Typing :: Typed
Classifier: Development Status :: 5 - Production/Stable
Classifier: License :: OSI Approved
Requires-Python: ~=3.7
License-File: LICENSE
